axon/__init__.py
axon/py.typed
axon/adapters/__init__.py
axon/adapters/base.py
axon/adapters/chroma.py
axon/adapters/memory.py
axon/adapters/pinecone.py
axon/adapters/qdrant.py
axon/adapters/redis.py
axon/core/__init__.py
axon/core/adapter_registry.py
axon/core/audit.py
axon/core/compaction_strategies.py
axon/core/config.py
axon/core/logging_config.py
axon/core/memory_system.py
axon/core/policy.py
axon/core/policy_engine.py
axon/core/privacy.py
axon/core/router.py
axon/core/scoring.py
axon/core/summarizer.py
axon/core/templates.py
axon/core/transaction.py
axon/core/policies/__init__.py
axon/core/policies/ephemeral.py
axon/core/policies/persistent.py
axon/core/policies/session.py
axon/embedders/__init__.py
axon/embedders/base.py
axon/embedders/cache.py
axon/embedders/huggingface.py
axon/embedders/openai.py
axon/embedders/sentence_transformer.py
axon/embedders/voyage.py
axon/integrations/__init__.py
axon/integrations/langchain/__init__.py
axon/integrations/langchain/memory.py
axon/integrations/langchain/vectorstore.py
axon/integrations/llamaindex/__init__.py
axon/integrations/llamaindex/vectorstore.py
axon/models/__init__.py
axon/models/audit.py
axon/models/base.py
axon/models/entry.py
axon/models/filter.py
axon/utils/__init__.py
axon_sdk-1.0.0b2.dist-info/METADATA
axon_sdk-1.0.0b2.dist-info/WHEEL
axon_sdk-1.0.0b2.dist-info/licenses/LICENSE
axon_sdk-1.0.0b2.dist-info/RECORD
