Metadata-Version: 2.4
Name: axon-sdk
Version: 1.0.0b2
Summary: Unified Memory SDK for LLM applications with multi-tier storage, policy-driven lifecycle, and intelligent summarization
Project-URL: Homepage, https://github.com/saranmahadev/Axon
Project-URL: Documentation, http://axon.saranmahadev.in
Project-URL: Repository, https://github.com/saranmahadev/Axon
Project-URL: Bug Tracker, https://github.com/saranmahadev/Axon/issues
Author-email: Saran Mahadev <saranmahadev8@gmail.com>
License: MIT
License-File: LICENSE
Keywords: ai,llm,machine-learning,memory,rag,vector-database
Classifier: Development Status :: 4 - Beta
Classifier: Intended Audience :: Developers
Classifier: License :: OSI Approved :: MIT License
Classifier: Programming Language :: Python :: 3
Classifier: Programming Language :: Python :: 3.10
Classifier: Programming Language :: Python :: 3.11
Classifier: Programming Language :: Python :: 3.12
Classifier: Topic :: Scientific/Engineering :: Artificial Intelligence
Classifier: Topic :: Software Development :: Libraries :: Python Modules
Requires-Python: >=3.10
Requires-Dist: numpy>=1.24.0
Requires-Dist: openai>=1.0.0
Requires-Dist: pydantic>=2.0.0
Requires-Dist: typing-extensions>=4.0.0
Provides-Extra: all
Requires-Dist: chromadb>=0.4.0; extra == 'all'
Requires-Dist: openai>=1.0.0; extra == 'all'
Requires-Dist: pinecone-client>=2.0.0; extra == 'all'
Requires-Dist: qdrant-client>=1.6.0; extra == 'all'
Requires-Dist: redis>=5.0.0; extra == 'all'
Provides-Extra: dev
Requires-Dist: black>=23.0.0; extra == 'dev'
Requires-Dist: mypy>=1.0.0; extra == 'dev'
Requires-Dist: pytest-asyncio>=0.21.0; extra == 'dev'
Requires-Dist: pytest-cov>=4.0.0; extra == 'dev'
Requires-Dist: pytest>=7.0.0; extra == 'dev'
Requires-Dist: ruff>=0.1.0; extra == 'dev'
